qdc_converter/__init__.py
qdc_converter/cli.py
qdc_converter/cli_multithreaded.py
qdc_converter/gui.py
qdc_converter/main.py
qdc_converter/utils.py
qdc_converter/version.py
qdc_converter/data/images/icon.icns
qdc_converter/data/images/icon.ico
qdc_converter/data/images/icon.png
qdc_converter/data/locale/ru/LC_MESSAGES/messages.mo
qdc_converter-2.6.dist-info/LICENSE
qdc_converter-2.6.dist-info/METADATA
qdc_converter-2.6.dist-info/WHEEL
qdc_converter-2.6.dist-info/entry_points.txt
qdc_converter-2.6.dist-info/top_level.txt
qdc_converter-2.6.dist-info/RECORD
