Metadata-Version: 2.1
Name: qdc-converter
Version: 2.6
Summary: Garmin QDC (Quickdraw Contours) Converter
Home-page: http://github.com/interlark/qdc-converter
Author: Andy Trofimov
Author-email: interlark@gmail.com
License: MIT
Keywords: qdc garmin converter
Platform: UNKNOWN
Classifier: License :: OSI Approved :: MIT License
Classifier: Operating System :: OS Independent
Classifier: Operating System :: MacOS
Classifier: Operating System :: Microsoft :: Windows
Classifier: Operating System :: POSIX
Classifier: Operating System :: Unix
Classifier: Programming Language :: Python
Classifier: Programming Language :: Python :: 3 :: Only
Classifier: Programming Language :: Python :: 3.6
Classifier: Programming Language :: Python :: 3.7
Classifier: Programming Language :: Python :: 3.8
Classifier: Programming Language :: Python :: 3.9
Classifier: Programming Language :: Python :: 3.10
Classifier: Intended Audience :: End Users/Desktop
Classifier: Topic :: Software Development
Classifier: Topic :: Terminals
Classifier: Topic :: Utilities
Requires-Python: >=3.6
Requires-Dist: numpy (>=1.19.0)
Requires-Dist: tqdm (>=4.37.0)
Requires-Dist: click (>=4.0.0)
Requires-Dist: click-option-group (>=0.5.3)
Requires-Dist: pebble (>=4.6.0)
Provides-Extra: dev
Requires-Dist: pyinstaller (>=5.0) ; extra == 'dev'
Requires-Dist: wheel (<0.38,>=0.36.2) ; extra == 'dev'
Requires-Dist: pre-commit (>=2.6) ; extra == 'dev'
Requires-Dist: pytest (<8,>=6.2) ; extra == 'dev'
Provides-Extra: gui
Requires-Dist: PySimpleGUI (==4.60.0) ; extra == 'gui'
